patpat/__init__.py
patpat/checker.py
patpat/hub.py
patpat/logger.py
patpat/mapper.py
patpat/querier.py
patpat/retriever.py
patpat/utility.py
patpat-1.1.1.dist-info/LICENSE
patpat-1.1.1.dist-info/METADATA
patpat-1.1.1.dist-info/WHEEL
patpat-1.1.1.dist-info/top_level.txt
patpat-1.1.1.dist-info/RECORD
