Metadata-Version: 2.1
Name: patpat
Version: 1.1.1
Summary: Patpat is public proteomics dataset search framework that only requires protein identifiers to be passed in to search for relevant datasets.
Author-email: Weiheng Liao <weiheng_liao@outlook.com>
License: Apache 2.0
Project-URL: Homepage, https://github.com/henry-leo/Patpat
Project-URL: Bug Tracker, https://github.com/henry-leo/Patpat/issues
Classifier: Programming Language :: Python :: 3
Classifier: Operating System :: OS Independent
Requires-Python: >=3.8
License-File: LICENSE
Requires-Dist: requests
Requires-Dist: tqdm
Requires-Dist: pyteomics (>=4.5.3)
Requires-Dist: pandas (>=1.4.3)
